[
    {
        "$type":"HyperQuest.GameServer.Contracts.CircleFieldSpec, HyperQuest.GameServer.Contracts",
        "StartRadius":3.5,
        "EndRadius":3.5,
        "TouchedEntitiesType":3,
        "AllianceFilter":6,
        "GameEntityTypeMask":-245,
        "Duration":{
            "$type":"HyperQuest.GameServer.Contracts.FixedFloatValueSpec, HyperQuest.GameServer.Contracts",
            "Value":5,
            "Tag":"SnowdisticCannonDoTDuration"
        },
        "CollisionCheckInterval":0.5,
        "OnEnterOperations":{
            "$type":"HyperQuest.GameServer.Contracts.CompositeOperationSpec, HyperQuest.GameServer.Contracts",
            "Operations":
            [
                {
                    "$type":"HyperQuest.GameServer.Contracts.BuffOperationSpec, HyperQuest.GameServer.Contracts",
                    "Buff":{
                        "$type":"HyperQuest.GameServer.Contracts.BuffSpecContainerRef, HyperQuest.GameServer.Contracts",
                        "SpecContainerReferenceId":854,
                        "Name":"SnowdisticCannon_LimitedEdition_VulnerabilityBuff"
                    },
                    "Target":{
                        "$type":"HyperQuest.GameServer.Contracts.OperationTargetSpec, HyperQuest.GameServer.Contracts"
                    }
                },
                {
                    "$type":"HyperQuest.GameServer.Contracts.DamageOperationSpec, HyperQuest.GameServer.Contracts",
                    "Value":{
                        "$type":"HyperQuest.GameServer.Contracts.StatValueSpec, HyperQuest.GameServer.Contracts",
                        "StatType":"SkillDamage",
                        "Tag":"SnowdisticCannonDoT"
                    },
                    "Target":{
                        "$type":"HyperQuest.GameServer.Contracts.OperationTargetSpec, HyperQuest.GameServer.Contracts"
                    }
                }
            ]
        },
        "OnTouchOperations":{
            "$type":"HyperQuest.GameServer.Contracts.CompositeOperationSpec, HyperQuest.GameServer.Contracts",
            "Operations":
            [
                {
                    "$type":"HyperQuest.GameServer.Contracts.BuffOperationSpec, HyperQuest.GameServer.Contracts",
                    "Buff":{
                        "$type":"HyperQuest.GameServer.Contracts.BuffSpecContainerRef, HyperQuest.GameServer.Contracts",
                        "SpecContainerReferenceId":854,
                        "Name":"SnowdisticCannon_LimitedEdition_VulnerabilityBuff"
                    },
                    "Target":{
                        "$type":"HyperQuest.GameServer.Contracts.OperationTargetSpec, HyperQuest.GameServer.Contracts"
                    }
                },
                {
                    "$type":"HyperQuest.GameServer.Contracts.DamageOperationSpec, HyperQuest.GameServer.Contracts",
                    "Value":{
                        "$type":"HyperQuest.GameServer.Contracts.StatValueSpec, HyperQuest.GameServer.Contracts",
                        "StatType":"SkillDamage"
                    },
                    "Target":{
                        "$type":"HyperQuest.GameServer.Contracts.OperationTargetSpec, HyperQuest.GameServer.Contracts"
                    }
                }
            ]
        },
        "OnExitOperations":{
            "$type":"HyperQuest.GameServer.Contracts.RemoveBuffOperationSpec, HyperQuest.GameServer.Contracts",
            "BuffReference":{
                "$type":"HyperQuest.GameServer.Contracts.BuffLabelReferenceSpec, HyperQuest.GameServer.Contracts"
            },
            "Target":{
                "$type":"HyperQuest.GameServer.Contracts.OperationTargetSpec, HyperQuest.GameServer.Contracts"
            }
        }
    }
]