{
    "OasisName":11611,
    "Level":26,
    "ForceCastleLevelOnBuildables":true,
    "AccountId":46,
    "AccountDisplayName":"Tarantuland",
    "LayoutId":1,
    "Rooms":
    [
        {
            "X":4,
            "Y":6,
            "Id":26,
            "SpecContainerId":22
        },
        {
            "Creatures":
            [
                {
                    "RoomZoneId":4,
                    "X":14,
                    "Y":33,
                    "Orientation":3,
                    "Id":106,
                    "SpecContainerId":1028
                },
                {
                    "RoomZoneId":4,
                    "X":16,
                    "Y":34,
                    "Orientation":3,
                    "Id":108,
                    "SpecContainerId":1028
                },
                {
                    "RoomZoneId":4,
                    "X":18,
                    "Y":34,
                    "Orientation":3,
                    "Id":377,
                    "SpecContainerId":1028
                },
                {
                    "RoomZoneId":4,
                    "X":22,
                    "Y":33,
                    "Orientation":3,
                    "Id":379,
                    "SpecContainerId":1028
                },
                {
                    "RoomZoneId":4,
                    "X":20,
                    "Y":33,
                    "Orientation":3,
                    "Id":111,
                    "SpecContainerId":1028
                },
                {
                    "RoomZoneId":4,
                    "X":20,
                    "Y":35,
                    "Orientation":3,
                    "Id":115,
                    "SpecContainerId":57
                },
                {
                    "RoomZoneId":4,
                    "X":18,
                    "Y":33,
                    "Orientation":3,
                    "Id":117,
                    "SpecContainerId":57
                }
            ],
            "Buildings":
            [
                {
                    "Rank":1,
                    "RoomZoneId":1,
                    "Id":16,
                    "SpecContainerId":1
                },
                {
                    "Rank":6,
                    "RoomZoneId":2,
                    "Id":17,
                    "SpecContainerId":3
                },
                {
                    "Rank":1,
                    "RoomZoneId":3,
                    "Id":18,
                    "SpecContainerId":4
                }
            ],
            "Y":6,
            "Id":29,
            "SpecContainerId":27
        },
        {
            "Creatures":
            [
                {
                    "AggroPropagationOffsetX":4.019638,
                    "AggroPropagationOffsetZ":-0.04033608,
                    "RoomZoneId":1,
                    "X":13,
                    "Y":2,
                    "Id":62,
                    "SpecContainerId":1028
                },
                {
                    "AggroPropagationOffsetX":-4.062832,
                    "AggroPropagationOffsetZ":0.00576207,
                    "RoomZoneId":1,
                    "X":22,
                    "Y":3,
                    "Orientation":2,
                    "Id":64,
                    "SpecContainerId":1028
                },
                {
                    "RoomZoneId":1,
                    "X":13,
                    "Y":31,
                    "Id":66,
                    "SpecContainerId":1028
                },
                {
                    "RoomZoneId":1,
                    "X":15,
                    "Y":29,
                    "Id":67,
                    "SpecContainerId":1028
                },
                {
                    "AggroPropagationOffsetX":-3.912111,
                    "AggroPropagationOffsetZ":0.8286005,
                    "RoomZoneId":1,
                    "X":21,
                    "Y":29,
                    "Orientation":3,
                    "Id":69,
                    "SpecContainerId":1028
                },
                {
                    "AggroPropagationOffsetX":0.3859279,
                    "AggroPropagationOffsetZ":1.026889,
                    "RoomZoneId":1,
                    "X":23,
                    "Y":13,
                    "Orientation":2,
                    "Id":70,
                    "SpecContainerId":1002
                },
                {
                    "RoomZoneId":1,
                    "X":12,
                    "Y":22,
                    "Id":71,
                    "SpecContainerId":1002
                },
                {
                    "AggroPropagationOffsetX":0.1579361,
                    "AggroPropagationOffsetZ":1.096222,
                    "RoomZoneId":1,
                    "X":32,
                    "Y":17,
                    "Orientation":2,
                    "Id":77,
                    "SpecContainerId":1028
                },
                {
                    "AggroPropagationOffsetX":-0.7161636,
                    "AggroPropagationOffsetZ":2.218243,
                    "RoomZoneId":1,
                    "X":32,
                    "Y":15,
                    "Orientation":2,
                    "Id":78,
                    "SpecContainerId":57
                },
                {
                    "AggroPropagationOffsetX":0.9018555,
                    "AggroPropagationOffsetZ":-0.9937705,
                    "RoomZoneId":1,
                    "X":30,
                    "Y":18,
                    "Orientation":2,
                    "Id":81,
                    "SpecContainerId":57
                },
                {
                    "AggroPropagationOffsetX":-0.1298752,
                    "AggroPropagationOffsetZ":-0.0098114,
                    "RoomZoneId":1,
                    "X":3,
                    "Y":22,
                    "Orientation":1,
                    "Id":85,
                    "SpecContainerId":1028
                },
                {
                    "RoomZoneId":1,
                    "X":1,
                    "Y":13,
                    "Orientation":3,
                    "Id":86,
                    "SpecContainerId":1028
                },
                {
                    "RoomZoneId":1,
                    "X":5,
                    "Y":13,
                    "Orientation":3,
                    "Id":87,
                    "SpecContainerId":1028
                },
                {
                    "AggroPropagationOffsetX":-3.212181,
                    "AggroPropagationOffsetZ":-0.205616,
                    "RoomZoneId":1,
                    "X":7,
                    "Y":13,
                    "Orientation":3,
                    "Id":88,
                    "SpecContainerId":1028
                },
                {
                    "RoomZoneId":1,
                    "X":1,
                    "Y":22,
                    "Orientation":1,
                    "Id":89,
                    "SpecContainerId":1028
                },
                {
                    "AggroPropagationOffsetX":-0.05298614,
                    "AggroPropagationOffsetZ":-2.407082,
                    "RoomZoneId":1,
                    "X":33,
                    "Y":20,
                    "Orientation":2,
                    "Id":124,
                    "SpecContainerId":1028
                },
                {
                    "RoomZoneId":1,
                    "X":33,
                    "Y":18,
                    "Orientation":2,
                    "Id":127,
                    "SpecContainerId":57
                },
                {
                    "AggroPropagationOffsetX":-4.079674,
                    "AggroPropagationOffsetZ":-0.2234982,
                    "RoomZoneId":1,
                    "X":22,
                    "Y":5,
                    "Orientation":2,
                    "Id":236,
                    "SpecContainerId":1028
                },
                {
                    "AggroPropagationOffsetX":4.022666,
                    "AggroPropagationOffsetZ":0.05038187,
                    "RoomZoneId":1,
                    "X":13,
                    "Y":4,
                    "Id":237,
                    "SpecContainerId":1028
                }
            ],
            "Traps":
            [
                {
                    "RoomZoneId":1,
                    "X":17,
                    "Y":17,
                    "Id":5,
                    "SpecContainerId":1004
                }
            ],
            "X":2,
            "Y":6,
            "Orientation":3,
            "Id":34,
            "SpecContainerId":5019
        },
        {
            "Creatures":
            [
                {
                    "RoomZoneId":1,
                    "X":5,
                    "Y":23,
                    "Orientation":1,
                    "Id":84,
                    "SpecContainerId":1007
                },
                {
                    "RoomZoneId":1,
                    "X":18,
                    "Y":1,
                    "Orientation":2,
                    "Id":91,
                    "SpecContainerId":1028
                },
                {
                    "AggroPropagationOffsetX":-2.383606,
                    "AggroPropagationOffsetZ":2.228683,
                    "RoomZoneId":1,
                    "X":14,
                    "Y":6,
                    "Orientation":2,
                    "Id":92,
                    "SpecContainerId":1028
                },
                {
                    "AggroPropagationOffsetX":-2.741378,
                    "AggroPropagationOffsetZ":-2.912876,
                    "RoomZoneId":1,
                    "X":14,
                    "Y":30,
                    "Orientation":2,
                    "Id":95,
                    "SpecContainerId":1028
                },
                {
                    "AggroPropagationOffsetX":-1.575613,
                    "AggroPropagationOffsetZ":-3.760968,
                    "RoomZoneId":1,
                    "X":2,
                    "Y":17,
                    "Orientation":2,
                    "Id":96,
                    "SpecContainerId":1028
                },
                {
                    "AggroPropagationOffsetX":-1.745827,
                    "AggroPropagationOffsetZ":-0.6628494,
                    "RoomZoneId":1,
                    "X":2,
                    "Y":19,
                    "Orientation":2,
                    "Id":98,
                    "SpecContainerId":57
                },
                {
                    "RoomZoneId":1,
                    "X":1,
                    "Y":18,
                    "Orientation":2,
                    "Id":119,
                    "SpecContainerId":57
                },
                {
                    "RoomZoneId":1,
                    "X":30,
                    "Y":5,
                    "Orientation":2,
                    "Id":120,
                    "SpecContainerId":1002
                },
                {
                    "RoomZoneId":1,
                    "X":30,
                    "Y":30,
                    "Orientation":2,
                    "Id":121,
                    "SpecContainerId":1002
                },
                {
                    "RoomZoneId":1,
                    "X":30,
                    "Y":6,
                    "Orientation":2,
                    "Id":122,
                    "SpecContainerId":1002
                },
                {
                    "RoomZoneId":1,
                    "X":30,
                    "Y":29,
                    "Orientation":2,
                    "Id":123,
                    "SpecContainerId":1002
                },
                {
                    "RoomZoneId":1,
                    "X":18,
                    "Y":34,
                    "Orientation":2,
                    "Id":311,
                    "SpecContainerId":1028
                },
                {
                    "RoomZoneId":1,
                    "X":29,
                    "Y":6,
                    "Orientation":2,
                    "Id":312,
                    "SpecContainerId":1028
                },
                {
                    "RoomZoneId":1,
                    "X":29,
                    "Y":30,
                    "Orientation":2,
                    "Id":313,
                    "SpecContainerId":1028
                },
                {
                    "AggroPropagationOffsetX":-2.71315,
                    "AggroPropagationOffsetZ":1.016289,
                    "RoomZoneId":1,
                    "X":35,
                    "Y":19,
                    "Orientation":2,
                    "Id":378,
                    "SpecContainerId":1028
                },
                {
                    "RoomZoneId":1,
                    "X":35,
                    "Y":17,
                    "Orientation":2,
                    "Id":116,
                    "SpecContainerId":57
                },
                {
                    "RoomZoneId":1,
                    "X":34,
                    "Y":15,
                    "Orientation":2,
                    "Id":118,
                    "SpecContainerId":57
                }
            ],
            "Traps":
            [
                {
                    "RoomZoneId":1,
                    "X":14,
                    "Y":1,
                    "Orientation":2,
                    "Id":13,
                    "SpecContainerId":1010
                },
                {
                    "RoomZoneId":1,
                    "X":14,
                    "Y":34,
                    "Orientation":2,
                    "Id":14,
                    "SpecContainerId":1000
                }
            ],
            "X":1,
            "Y":6,
            "Orientation":1,
            "Id":35,
            "SpecContainerId":7059
        },
        {
            "Creatures":
            [
                {
                    "RoomZoneId":1,
                    "X":17,
                    "Y":12,
                    "Orientation":3,
                    "Id":58,
                    "SpecContainerId":1028
                },
                {
                    "AggroPropagationOffsetX":0.1265945,
                    "AggroPropagationOffsetZ":1.089489,
                    "RoomZoneId":1,
                    "X":14,
                    "Y":17,
                    "Id":176,
                    "SpecContainerId":1015
                },
                {
                    "AggroPropagationOffsetX":-0.4108302,
                    "AggroPropagationOffsetZ":-1.923436,
                    "RoomZoneId":1,
                    "X":21,
                    "Y":18,
                    "Orientation":2,
                    "Id":177,
                    "SpecContainerId":1015
                },
                {
                    "RoomZoneId":1,
                    "X":12,
                    "Y":16,
                    "Id":230,
                    "SpecContainerId":1028
                },
                {
                    "RoomZoneId":1,
                    "X":12,
                    "Y":18,
                    "Id":231,
                    "SpecContainerId":1028
                },
                {
                    "RoomZoneId":1,
                    "X":23,
                    "Y":17,
                    "Orientation":2,
                    "Id":232,
                    "SpecContainerId":1028
                },
                {
                    "RoomZoneId":1,
                    "X":19,
                    "Y":12,
                    "Orientation":3,
                    "Id":233,
                    "SpecContainerId":1028
                },
                {
                    "RoomZoneId":1,
                    "X":17,
                    "Y":23,
                    "Orientation":1,
                    "Id":234,
                    "SpecContainerId":1028
                },
                {
                    "RoomZoneId":1,
                    "X":23,
                    "Y":19,
                    "Orientation":2,
                    "Id":235,
                    "SpecContainerId":1028
                }
            ],
            "Traps":
            [
                {
                    "RoomZoneId":1,
                    "X":17,
                    "Y":26,
                    "Orientation":1,
                    "Id":11,
                    "SpecContainerId":1004
                },
                {
                    "RoomZoneId":1,
                    "X":18,
                    "Y":9,
                    "Orientation":3,
                    "Id":12,
                    "SpecContainerId":1004
                }
            ],
            "X":2,
            "Y":5,
            "Id":36,
            "SpecContainerId":5020
        },
        {
            "Creatures":
            [
                {
                    "AggroPropagationOffsetX":1.092148,
                    "AggroPropagationOffsetZ":-1.004616,
                    "RoomZoneId":1,
                    "X":17,
                    "Y":21,
                    "Orientation":3,
                    "Id":7,
                    "SpecContainerId":1006
                },
                {
                    "RoomZoneId":1,
                    "X":7,
                    "Y":29,
                    "Id":150,
                    "SpecContainerId":1028
                },
                {
                    "RoomZoneId":1,
                    "X":15,
                    "Y":21,
                    "Orientation":3,
                    "Id":151,
                    "SpecContainerId":1028
                },
                {
                    "AggroPropagationOffsetX":0.9147797,
                    "AggroPropagationOffsetZ":0.4154663,
                    "RoomZoneId":1,
                    "X":19,
                    "Y":21,
                    "Orientation":3,
                    "Id":152,
                    "SpecContainerId":1028
                },
                {
                    "RoomZoneId":1,
                    "X":21,
                    "Y":21,
                    "Orientation":3,
                    "Id":154,
                    "SpecContainerId":1028
                },
                {
                    "RoomZoneId":1,
                    "X":22,
                    "Y":1,
                    "Orientation":3,
                    "Id":157,
                    "SpecContainerId":1002
                },
                {
                    "RoomZoneId":1,
                    "X":22,
                    "Y":3,
                    "Orientation":3,
                    "Id":158,
                    "SpecContainerId":57
                },
                {
                    "RoomZoneId":1,
                    "X":21,
                    "Y":1,
                    "Orientation":3,
                    "Id":159,
                    "SpecContainerId":57
                },
                {
                    "AggroPropagationOffsetX":-0.3462448,
                    "AggroPropagationOffsetZ":0.8996887,
                    "RoomZoneId":1,
                    "X":17,
                    "Y":3,
                    "Orientation":3,
                    "Id":160,
                    "SpecContainerId":57
                },
                {
                    "RoomZoneId":1,
                    "X":14,
                    "Y":3,
                    "Orientation":3,
                    "Id":161,
                    "SpecContainerId":57
                },
                {
                    "RoomZoneId":1,
                    "X":19,
                    "Y":1,
                    "Orientation":3,
                    "Id":162,
                    "SpecContainerId":57
                },
                {
                    "RoomZoneId":1,
                    "X":1,
                    "Y":19,
                    "Id":170,
                    "SpecContainerId":440
                },
                {
                    "RoomZoneId":1,
                    "X":1,
                    "Y":18,
                    "Id":171,
                    "SpecContainerId":440
                },
                {
                    "RoomZoneId":1,
                    "X":1,
                    "Y":16,
                    "Id":173,
                    "SpecContainerId":440
                },
                {
                    "RoomZoneId":1,
                    "X":1,
                    "Y":17,
                    "Id":174,
                    "SpecContainerId":440
                },
                {
                    "RoomZoneId":1,
                    "X":30,
                    "Y":17,
                    "Orientation":2,
                    "Id":178,
                    "SpecContainerId":440
                },
                {
                    "RoomZoneId":1,
                    "X":30,
                    "Y":18,
                    "Orientation":2,
                    "Id":179,
                    "SpecContainerId":440
                },
                {
                    "RoomZoneId":1,
                    "X":16,
                    "Y":23,
                    "Orientation":3,
                    "Id":382,
                    "SpecContainerId":1028
                },
                {
                    "RoomZoneId":1,
                    "X":20,
                    "Y":23,
                    "Orientation":3,
                    "Id":383,
                    "SpecContainerId":1028
                },
                {
                    "AggroPropagationOffsetX":0.4448242,
                    "AggroPropagationOffsetZ":-1.407692,
                    "RoomZoneId":1,
                    "X":18,
                    "Y":1,
                    "Orientation":3,
                    "Id":384,
                    "SpecContainerId":1028
                },
                {
                    "RoomZoneId":1,
                    "X":14,
                    "Y":1,
                    "Orientation":3,
                    "Id":385,
                    "SpecContainerId":1028
                }
            ],
            "Traps":
            [
                {
                    "RoomZoneId":1,
                    "X":17,
                    "Y":26,
                    "Orientation":1,
                    "Id":3,
                    "SpecContainerId":1004
                },
                {
                    "RoomZoneId":1,
                    "X":17,
                    "Y":10,
                    "Orientation":1,
                    "Id":10,
                    "SpecContainerId":1004
                }
            ],
            "X":2,
            "Y":7,
            "Id":37,
            "SpecContainerId":5015
        },
        {
            "Creatures":
            [
                {
                    "RoomZoneId":1,
                    "X":22,
                    "Y":8,
                    "Orientation":3,
                    "Id":6,
                    "SpecContainerId":440
                },
                {
                    "RoomZoneId":1,
                    "X":21,
                    "Y":8,
                    "Orientation":3,
                    "Id":130,
                    "SpecContainerId":440
                },
                {
                    "RoomZoneId":1,
                    "X":21,
                    "Y":7,
                    "Orientation":3,
                    "Id":131,
                    "SpecContainerId":440
                },
                {
                    "RoomZoneId":1,
                    "X":22,
                    "Y":7,
                    "Orientation":3,
                    "Id":132,
                    "SpecContainerId":440
                },
                {
                    "RoomZoneId":1,
                    "X":10,
                    "Y":17,
                    "Orientation":2,
                    "Id":133,
                    "SpecContainerId":440
                },
                {
                    "RoomZoneId":1,
                    "X":17,
                    "Y":25,
                    "Orientation":3,
                    "Id":134,
                    "SpecContainerId":440
                },
                {
                    "RoomZoneId":1,
                    "X":22,
                    "Y":2,
                    "Orientation":2,
                    "Id":139,
                    "SpecContainerId":1028
                },
                {
                    "RoomZoneId":1,
                    "X":22,
                    "Y":4,
                    "Orientation":2,
                    "Id":140,
                    "SpecContainerId":1028
                },
                {
                    "RoomZoneId":1,
                    "X":1,
                    "Y":15,
                    "Id":143,
                    "SpecContainerId":1028
                },
                {
                    "RoomZoneId":1,
                    "X":1,
                    "Y":19,
                    "Id":144,
                    "SpecContainerId":1028
                },
                {
                    "RoomZoneId":1,
                    "X":18,
                    "Y":34,
                    "Orientation":1,
                    "Id":146,
                    "SpecContainerId":1028
                },
                {
                    "RoomZoneId":1,
                    "X":2,
                    "Y":17,
                    "Id":147,
                    "SpecContainerId":1028
                },
                {
                    "RoomZoneId":1,
                    "X":13,
                    "Y":1,
                    "Id":380,
                    "SpecContainerId":1028
                },
                {
                    "RoomZoneId":1,
                    "X":13,
                    "Y":3,
                    "Id":381,
                    "SpecContainerId":1028
                }
            ],
            "Traps":
            [
                {
                    "RoomZoneId":1,
                    "X":25,
                    "Y":10,
                    "Orientation":3,
                    "Id":2,
                    "SpecContainerId":1010
                }
            ],
            "X":3,
            "Y":7,
            "Id":38,
            "SpecContainerId":5022
        },
        {
            "Creatures":
            [
                {
                    "RoomZoneId":1,
                    "X":14,
                    "Y":3,
                    "Orientation":3,
                    "Id":32,
                    "SpecContainerId":1015
                },
                {
                    "AggroPropagationOffsetX":0.0424881,
                    "AggroPropagationOffsetZ":-4.111038,
                    "RoomZoneId":1,
                    "X":26,
                    "Y":21,
                    "Orientation":3,
                    "Id":40,
                    "SpecContainerId":1028
                },
                {
                    "RoomZoneId":1,
                    "X":13,
                    "Y":32,
                    "Orientation":1,
                    "Id":42,
                    "SpecContainerId":1015
                },
                {
                    "AggroPropagationOffsetX":-0.2179781,
                    "AggroPropagationOffsetZ":3.168794,
                    "RoomZoneId":1,
                    "X":32,
                    "Y":22,
                    "Orientation":2,
                    "Id":45,
                    "SpecContainerId":1015
                },
                {
                    "RoomZoneId":1,
                    "X":30,
                    "Y":5,
                    "Orientation":3,
                    "Id":48,
                    "SpecContainerId":1002
                },
                {
                    "AggroPropagationOffsetX":0.7110519,
                    "AggroPropagationOffsetZ":-1.823189,
                    "RoomZoneId":1,
                    "X":26,
                    "Y":5,
                    "Orientation":3,
                    "Id":51,
                    "SpecContainerId":57
                },
                {
                    "RoomZoneId":1,
                    "X":28,
                    "Y":6,
                    "Orientation":3,
                    "Id":52,
                    "SpecContainerId":57
                },
                {
                    "AggroPropagationOffsetX":-0.8950042,
                    "AggroPropagationOffsetZ":1.985864,
                    "RoomZoneId":1,
                    "X":30,
                    "Y":7,
                    "Orientation":2,
                    "Id":53,
                    "SpecContainerId":57
                },
                {
                    "RoomZoneId":1,
                    "X":29,
                    "Y":5,
                    "Orientation":3,
                    "Id":129,
                    "SpecContainerId":57
                },
                {
                    "RoomZoneId":1,
                    "X":14,
                    "Y":10,
                    "Orientation":2,
                    "Id":375,
                    "SpecContainerId":1028
                },
                {
                    "RoomZoneId":1,
                    "X":5,
                    "Y":30,
                    "Orientation":1,
                    "Id":376,
                    "SpecContainerId":1028
                }
            ],
            "Traps":
            [
                {
                    "RoomZoneId":1,
                    "X":9,
                    "Y":8,
                    "Orientation":3,
                    "Id":1,
                    "SpecContainerId":1000
                }
            ],
            "X":3,
            "Y":5,
            "Id":39,
            "SpecContainerId":7058
        },
        {
            "Creatures":
            [
                {
                    "RoomZoneId":1,
                    "X":7,
                    "Y":5,
                    "Orientation":3,
                    "Id":8,
                    "SpecContainerId":1002
                },
                {
                    "RoomZoneId":1,
                    "X":9,
                    "Y":21,
                    "Orientation":3,
                    "Id":17,
                    "SpecContainerId":1028
                },
                {
                    "AggroPropagationOffsetX":-0.1224365,
                    "AggroPropagationOffsetZ":0.1225052,
                    "RoomZoneId":1,
                    "X":19,
                    "Y":13,
                    "Orientation":1,
                    "Id":19,
                    "SpecContainerId":1028
                },
                {
                    "AggroPropagationOffsetX":-0.2052422,
                    "AggroPropagationOffsetZ":-1.661072,
                    "RoomZoneId":1,
                    "X":15,
                    "Y":13,
                    "Orientation":1,
                    "Id":20,
                    "SpecContainerId":1028
                },
                {
                    "RoomZoneId":1,
                    "X":18,
                    "Y":30,
                    "Orientation":3,
                    "Id":22,
                    "SpecContainerId":1028
                },
                {
                    "RoomZoneId":1,
                    "X":16,
                    "Y":30,
                    "Orientation":3,
                    "Id":23,
                    "SpecContainerId":57
                },
                {
                    "RoomZoneId":1,
                    "X":19,
                    "Y":29,
                    "Orientation":3,
                    "Id":24,
                    "SpecContainerId":57
                },
                {
                    "RoomZoneId":1,
                    "X":20,
                    "Y":30,
                    "Orientation":3,
                    "Id":25,
                    "SpecContainerId":57
                },
                {
                    "RoomZoneId":1,
                    "X":5,
                    "Y":5,
                    "Orientation":3,
                    "Id":26,
                    "SpecContainerId":57
                },
                {
                    "RoomZoneId":1,
                    "X":6,
                    "Y":6,
                    "Orientation":3,
                    "Id":27,
                    "SpecContainerId":57
                },
                {
                    "RoomZoneId":1,
                    "X":5,
                    "Y":8,
                    "Id":28,
                    "SpecContainerId":57
                },
                {
                    "RoomZoneId":1,
                    "X":29,
                    "Y":5,
                    "Orientation":2,
                    "Id":29,
                    "SpecContainerId":57
                },
                {
                    "RoomZoneId":1,
                    "X":30,
                    "Y":7,
                    "Orientation":2,
                    "Id":30,
                    "SpecContainerId":57
                },
                {
                    "RoomZoneId":1,
                    "X":27,
                    "Y":6,
                    "Orientation":3,
                    "Id":31,
                    "SpecContainerId":57
                }
            ],
            "X":3,
            "Y":6,
            "Id":42,
            "SpecContainerId":4003
        }
    ],
    "CreatureTiers":
    [
        {
            "SpecContainerId":1,
            "Tier":7
        },
        {
            "SpecContainerId":57,
            "Tier":9
        },
        {
            "SpecContainerId":440,
            "Tier":5
        },
        {
            "SpecContainerId":20,
            "Tier":5,
            "Specialization":2
        },
        {
            "SpecContainerId":50,
            "Tier":4
        }
    ],
    "TrapTiers":
    [
        {
            "SpecContainerId":9,
            "Tier":4
        }
    ],
    "ThemeId":2
}