{
    "OasisName":2525,
    "Level":11,
    "ForceCastleLevelOnBuildables":true,
    "AccountId":28,
    "AccountDisplayName":"Good Doggy",
    "LayoutId":1,
    "Rooms":
    [
        {
            "X":4,
            "Y":5,
            "Id":26,
            "SpecContainerId":22
        },
        {
            "Buildings":
            [
                {
                    "Rank":14,
                    "RoomZoneId":1,
                    "Id":16,
                    "SpecContainerId":1
                },
                {
                    "Rank":1,
                    "RoomZoneId":2,
                    "Id":17,
                    "SpecContainerId":3
                },
                {
                    "Rank":1,
                    "RoomZoneId":3,
                    "Id":18,
                    "SpecContainerId":4
                }
            ],
            "X":3,
            "Y":3,
            "Orientation":3,
            "Id":29,
            "SpecContainerId":27
        },
        {
            "Creatures":
            [
                {
                    "RoomZoneId":1,
                    "X":27,
                    "Y":30,
                    "Orientation":1,
                    "Id":1,
                    "SpecContainerId":1001
                },
                {
                    "RoomZoneId":1,
                    "X":26,
                    "Y":29,
                    "Id":12,
                    "SpecContainerId":1001
                },
                {
                    "RoomZoneId":1,
                    "X":27,
                    "Y":28,
                    "Orientation":3,
                    "Id":13,
                    "SpecContainerId":1001
                },
                {
                    "RoomZoneId":1,
                    "X":22,
                    "Y":18,
                    "Id":14,
                    "SpecContainerId":1001
                },
                {
                    "RoomZoneId":1,
                    "X":22,
                    "Y":17,
                    "Id":15,
                    "SpecContainerId":1001
                },
                {
                    "RoomZoneId":1,
                    "X":5,
                    "Y":30,
                    "Orientation":1,
                    "Id":17,
                    "SpecContainerId":1002
                },
                {
                    "AggroPropagationOffsetX":-2.199898,
                    "AggroPropagationOffsetZ":2.748945,
                    "RoomZoneId":1,
                    "X":5,
                    "Y":14,
                    "Orientation":2,
                    "Id":18,
                    "SpecContainerId":1001
                },
                {
                    "RoomZoneId":1,
                    "X":6,
                    "Y":30,
                    "Orientation":1,
                    "Id":19,
                    "SpecContainerId":1002
                },
                {
                    "AggroPropagationOffsetX":2.303717,
                    "AggroPropagationOffsetZ":-3.337413,
                    "RoomZoneId":1,
                    "X":11,
                    "Y":18,
                    "Orientation":1,
                    "Id":20,
                    "SpecContainerId":1002
                },
                {
                    "RoomZoneId":1,
                    "X":27,
                    "Y":29,
                    "Orientation":1,
                    "Id":21,
                    "SpecContainerId":1002
                },
                {
                    "RoomZoneId":1,
                    "X":28,
                    "Y":29,
                    "Orientation":2,
                    "Id":22,
                    "SpecContainerId":1001
                },
                {
                    "RoomZoneId":1,
                    "X":17,
                    "Y":6,
                    "Orientation":1,
                    "Id":51,
                    "SpecContainerId":1010
                }
            ],
            "Traps":
            [
                {
                    "RoomZoneId":1,
                    "X":7,
                    "Y":8,
                    "Orientation":1,
                    "Id":1,
                    "SpecContainerId":13
                },
                {
                    "RoomZoneId":1,
                    "X":27,
                    "Y":8,
                    "Orientation":1,
                    "Id":6,
                    "SpecContainerId":13
                },
                {
                    "RoomZoneId":1,
                    "X":19,
                    "Y":32,
                    "Orientation":3,
                    "Id":3,
                    "SpecContainerId":1005
                }
            ],
            "X":3,
            "Y":5,
            "Orientation":2,
            "Id":32,
            "SpecContainerId":2005
        },
        {
            "Creatures":
            [
                {
                    "RoomZoneId":1,
                    "X":8,
                    "Y":23,
                    "Orientation":3,
                    "Id":8,
                    "SpecContainerId":1003
                },
                {
                    "RoomZoneId":1,
                    "X":6,
                    "Y":12,
                    "Id":27,
                    "SpecContainerId":1001
                },
                {
                    "RoomZoneId":1,
                    "X":8,
                    "Y":12,
                    "Orientation":2,
                    "Id":28,
                    "SpecContainerId":1001
                },
                {
                    "RoomZoneId":1,
                    "X":7,
                    "Y":11,
                    "Orientation":3,
                    "Id":29,
                    "SpecContainerId":1001
                },
                {
                    "RoomZoneId":1,
                    "X":17,
                    "Y":16,
                    "Orientation":3,
                    "Id":30,
                    "SpecContainerId":1001
                },
                {
                    "RoomZoneId":1,
                    "X":17,
                    "Y":17,
                    "Orientation":1,
                    "Id":31,
                    "SpecContainerId":1001
                },
                {
                    "RoomZoneId":1,
                    "X":17,
                    "Y":19,
                    "Orientation":1,
                    "Id":32,
                    "SpecContainerId":1009
                },
                {
                    "RoomZoneId":1,
                    "X":29,
                    "Y":15,
                    "Orientation":1,
                    "Id":33,
                    "SpecContainerId":1003
                },
                {
                    "RoomZoneId":1,
                    "X":28,
                    "Y":12,
                    "Orientation":3,
                    "Id":36,
                    "SpecContainerId":1001
                },
                {
                    "RoomZoneId":1,
                    "X":29,
                    "Y":12,
                    "Orientation":3,
                    "Id":37,
                    "SpecContainerId":1001
                },
                {
                    "RoomZoneId":1,
                    "X":30,
                    "Y":12,
                    "Orientation":3,
                    "Id":38,
                    "SpecContainerId":1001
                },
                {
                    "RoomZoneId":1,
                    "X":28,
                    "Y":11,
                    "Orientation":3,
                    "Id":48,
                    "SpecContainerId":1001
                },
                {
                    "RoomZoneId":1,
                    "X":29,
                    "Y":11,
                    "Orientation":3,
                    "Id":49,
                    "SpecContainerId":1001
                },
                {
                    "RoomZoneId":1,
                    "X":30,
                    "Y":11,
                    "Orientation":3,
                    "Id":50,
                    "SpecContainerId":1001
                },
                {
                    "RoomZoneId":1,
                    "X":6,
                    "Y":26,
                    "Orientation":1,
                    "Id":55,
                    "SpecContainerId":1001
                },
                {
                    "RoomZoneId":1,
                    "X":7,
                    "Y":26,
                    "Orientation":1,
                    "Id":56,
                    "SpecContainerId":1001
                },
                {
                    "RoomZoneId":1,
                    "X":8,
                    "Y":26,
                    "Orientation":1,
                    "Id":57,
                    "SpecContainerId":1001
                }
            ],
            "Traps":
            [
                {
                    "RoomZoneId":1,
                    "X":17,
                    "Y":9,
                    "Id":5,
                    "SpecContainerId":1003
                },
                {
                    "RoomZoneId":1,
                    "X":17,
                    "Y":29,
                    "Id":4,
                    "SpecContainerId":1003
                }
            ],
            "X":2,
            "Y":4,
            "Orientation":3,
            "Id":33,
            "SpecContainerId":7068
        },
        {
            "Creatures":
            [
                {
                    "AggroPropagationOffsetX":-0.3135056,
                    "AggroPropagationOffsetZ":-4.070635,
                    "RoomZoneId":1,
                    "X":16,
                    "Y":22,
                    "Orientation":1,
                    "Id":42,
                    "SpecContainerId":1026
                },
                {
                    "RoomZoneId":1,
                    "X":17,
                    "Y":28,
                    "Orientation":1,
                    "Id":44,
                    "SpecContainerId":1009
                },
                {
                    "RoomZoneId":1,
                    "X":24,
                    "Y":9,
                    "Orientation":3,
                    "Id":53,
                    "SpecContainerId":1002
                },
                {
                    "RoomZoneId":1,
                    "X":2,
                    "Y":22,
                    "Orientation":1,
                    "Id":91,
                    "SpecContainerId":1001
                },
                {
                    "RoomZoneId":1,
                    "X":1,
                    "Y":22,
                    "Orientation":1,
                    "Id":92,
                    "SpecContainerId":1001
                },
                {
                    "RoomZoneId":1,
                    "X":2,
                    "Y":21,
                    "Orientation":1,
                    "Id":93,
                    "SpecContainerId":1001
                },
                {
                    "RoomZoneId":1,
                    "X":1,
                    "Y":21,
                    "Orientation":1,
                    "Id":94,
                    "SpecContainerId":1001
                },
                {
                    "RoomZoneId":1,
                    "X":2,
                    "Y":13,
                    "Orientation":3,
                    "Id":101,
                    "SpecContainerId":1001
                },
                {
                    "RoomZoneId":1,
                    "X":1,
                    "Y":13,
                    "Orientation":3,
                    "Id":102,
                    "SpecContainerId":1001
                },
                {
                    "RoomZoneId":1,
                    "X":1,
                    "Y":14,
                    "Orientation":3,
                    "Id":103,
                    "SpecContainerId":1001
                },
                {
                    "RoomZoneId":1,
                    "X":2,
                    "Y":14,
                    "Orientation":3,
                    "Id":104,
                    "SpecContainerId":1001
                },
                {
                    "RoomZoneId":1,
                    "X":31,
                    "Y":17,
                    "Id":109,
                    "SpecContainerId":1001
                },
                {
                    "RoomZoneId":1,
                    "X":31,
                    "Y":18,
                    "Id":110,
                    "SpecContainerId":1001
                },
                {
                    "RoomZoneId":1,
                    "X":2,
                    "Y":15,
                    "Orientation":3,
                    "Id":123,
                    "SpecContainerId":1001
                },
                {
                    "RoomZoneId":1,
                    "X":1,
                    "Y":15,
                    "Orientation":3,
                    "Id":124,
                    "SpecContainerId":1001
                },
                {
                    "RoomZoneId":1,
                    "X":2,
                    "Y":20,
                    "Orientation":1,
                    "Id":125,
                    "SpecContainerId":1001
                },
                {
                    "RoomZoneId":1,
                    "X":1,
                    "Y":20,
                    "Orientation":1,
                    "Id":126,
                    "SpecContainerId":1001
                },
                {
                    "AggroPropagationOffsetX":3.329649,
                    "AggroPropagationOffsetZ":2.245345,
                    "RoomZoneId":1,
                    "X":7,
                    "Y":17,
                    "Id":145,
                    "SpecContainerId":1001
                },
                {
                    "AggroPropagationOffsetX":3.447446,
                    "AggroPropagationOffsetZ":-2.028575,
                    "RoomZoneId":1,
                    "X":7,
                    "Y":18,
                    "Id":146,
                    "SpecContainerId":1001
                },
                {
                    "RoomZoneId":1,
                    "X":2,
                    "Y":19,
                    "Orientation":1,
                    "Id":147,
                    "SpecContainerId":1001
                },
                {
                    "RoomZoneId":1,
                    "X":1,
                    "Y":19,
                    "Orientation":1,
                    "Id":148,
                    "SpecContainerId":1001
                },
                {
                    "RoomZoneId":1,
                    "X":2,
                    "Y":16,
                    "Orientation":3,
                    "Id":149,
                    "SpecContainerId":1001
                },
                {
                    "RoomZoneId":1,
                    "X":1,
                    "Y":16,
                    "Orientation":3,
                    "Id":150,
                    "SpecContainerId":1001
                },
                {
                    "RoomZoneId":1,
                    "X":17,
                    "Y":30,
                    "Orientation":1,
                    "Id":168,
                    "SpecContainerId":1009
                },
                {
                    "RoomZoneId":1,
                    "X":17,
                    "Y":26,
                    "Orientation":1,
                    "Id":169,
                    "SpecContainerId":1009
                },
                {
                    "AggroPropagationOffsetX":0.3984998,
                    "AggroPropagationOffsetZ":-4.084972,
                    "RoomZoneId":1,
                    "X":18,
                    "Y":22,
                    "Orientation":1,
                    "Id":170,
                    "SpecContainerId":1026
                },
                {
                    "AggroPropagationOffsetX":0.286644,
                    "AggroPropagationOffsetZ":-2.204403,
                    "RoomZoneId":1,
                    "X":17,
                    "Y":24,
                    "Orientation":1,
                    "Id":172,
                    "SpecContainerId":1026
                }
            ],
            "Traps":
            [
                {
                    "RoomZoneId":1,
                    "X":23,
                    "Y":16,
                    "Id":2,
                    "SpecContainerId":1005
                }
            ],
            "X":3,
            "Y":4,
            "Orientation":1,
            "Id":34,
            "SpecContainerId":7066
        },
        {
            "Creatures":
            [
                {
                    "RoomZoneId":1,
                    "X":19,
                    "Y":19,
                    "Orientation":2,
                    "Id":10,
                    "SpecContainerId":1009
                },
                {
                    "RoomZoneId":1,
                    "X":30,
                    "Y":24,
                    "Orientation":2,
                    "Id":2,
                    "SpecContainerId":1002
                },
                {
                    "RoomZoneId":1,
                    "X":30,
                    "Y":25,
                    "Orientation":1,
                    "Id":23,
                    "SpecContainerId":1002
                },
                {
                    "RoomZoneId":1,
                    "X":16,
                    "Y":19,
                    "Id":24,
                    "SpecContainerId":1009
                },
                {
                    "RoomZoneId":1,
                    "X":18,
                    "Y":16,
                    "Orientation":3,
                    "Id":25,
                    "SpecContainerId":1009
                },
                {
                    "RoomZoneId":1,
                    "X":9,
                    "Y":7,
                    "Orientation":2,
                    "Id":54,
                    "SpecContainerId":1002
                },
                {
                    "RoomZoneId":1,
                    "X":9,
                    "Y":5,
                    "Orientation":1,
                    "Id":87,
                    "SpecContainerId":1002
                },
                {
                    "RoomZoneId":1,
                    "X":10,
                    "Y":5,
                    "Orientation":1,
                    "Id":88,
                    "SpecContainerId":1002
                },
                {
                    "RoomZoneId":1,
                    "X":26,
                    "Y":6,
                    "Orientation":1,
                    "Id":89,
                    "SpecContainerId":1002
                },
                {
                    "RoomZoneId":1,
                    "X":26,
                    "Y":5,
                    "Id":90,
                    "SpecContainerId":1002
                },
                {
                    "RoomZoneId":1,
                    "X":25,
                    "Y":5,
                    "Orientation":1,
                    "Id":41,
                    "SpecContainerId":1002
                },
                {
                    "RoomZoneId":1,
                    "X":11,
                    "Y":5,
                    "Orientation":3,
                    "Id":155,
                    "SpecContainerId":1002
                },
                {
                    "RoomZoneId":1,
                    "X":9,
                    "Y":6,
                    "Orientation":3,
                    "Id":156,
                    "SpecContainerId":1002
                },
                {
                    "RoomZoneId":1,
                    "X":10,
                    "Y":6,
                    "Orientation":3,
                    "Id":157,
                    "SpecContainerId":1002
                },
                {
                    "RoomZoneId":1,
                    "X":24,
                    "Y":5,
                    "Orientation":3,
                    "Id":159,
                    "SpecContainerId":1002
                },
                {
                    "RoomZoneId":1,
                    "X":25,
                    "Y":6,
                    "Orientation":3,
                    "Id":160,
                    "SpecContainerId":1002
                },
                {
                    "RoomZoneId":1,
                    "X":26,
                    "Y":7,
                    "Orientation":3,
                    "Id":161,
                    "SpecContainerId":1002
                }
            ],
            "X":2,
            "Y":5,
            "Id":35,
            "SpecContainerId":3001
        }
    ],
    "CreatureTiers":
    [
        {
            "SpecContainerId":1,
            "Tier":3
        },
        {
            "SpecContainerId":434,
            "Tier":5
        }
    ],
    "TrapTiers":
    [
        {
            "SpecContainerId":13,
            "Tier":4
        },
        {
            "SpecContainerId":2
        }
    ],
    "ThemeId":3
}