[
    {
        "$type":"HyperQuest.GameServer.Contracts.VisualSpec, HyperQuest.GameServer.Contracts",
        "SynergyName":"CHA_025_ShockerLT_Beam",
        "Scale":1.5
    },
    {
        "$type":"HyperQuest.GameServer.Contracts.VisualAbilitySpec, HyperQuest.GameServer.Contracts",
        "Levels":
        [
            {
                "AnimPrepare":"00_Attack"
            }
        ]
    },
    {
        "$type":"HyperQuest.GameServer.Contracts.VisualFxAbilitiesLevelSpec, HyperQuest.GameServer.Contracts",
        "Levels":
        [
            {
                "StartFx":
                [
                    {
                        "Fx":{
                            "$type":"HyperQuest.GameServer.Contracts.VisualSpecialEffectNodeFxSpec, HyperQuest.GameServer.Contracts",
                            "SynergyEntityFileName":"DB:>RAW>SPECIALEFFECTS>FX_FC87D288>FX_FC87D288.SPECIALFX",
                            "AttachmentStrategy":{
                                "$type":"HyperQuest.GameServer.Contracts.VisualBoneAttachmentStrategySpec, HyperQuest.GameServer.Contracts",
                                "BoneName":"FX_Body"
                            }
                        },
                        "PlayUntil":"ActiveEnd"
                    }
                ],
                "PrepareFx":
                [
                    {
                        "Fx":{
                            "$type":"HyperQuest.GameServer.Contracts.VisualSpecialEffectNodeFxSpec, HyperQuest.GameServer.Contracts",
                            "SynergyEntityFileName":"DB:>RAW>SPECIALEFFECTS>SPECIALFX_E886962B_AI933>SPECIALFX_E886962B_AI933.SPECIALFX",
                            "AttachmentStrategy":{
                                "$type":"HyperQuest.GameServer.Contracts.VisualNodeAttachmentStrategySpec, HyperQuest.GameServer.Contracts",
                                "HeightOffset":1.45,
                                "FrontOffset":0.9
                            }
                        },
                        "PlayUntil":"PrepareEnd"
                    }
                ]
            }
        ]
    },
    {
        "$type":"HyperQuest.GameServer.Contracts.VisualAnimationTagFxSpec, HyperQuest.GameServer.Contracts",
        "Fx":
        [
            {
                "$type":"HyperQuest.GameServer.Contracts.VisualSpecialEffectNodeFxSpec, HyperQuest.GameServer.Contracts",
                "SynergyEntityFileName":"DB:>RAW>SPECIALEFFECTS>FX_354C4EA8_AI933>FX_354C4EA8_AI933.SPECIALFX",
                "AttachmentStrategy":{
                    "$type":"HyperQuest.GameServer.Contracts.VisualBoneAttachmentStrategySpec, HyperQuest.GameServer.Contracts",
                    "BoneName":"FX_Body"
                },
                "ForcePlayUntilFxFinished":true
            }
        ]
    }
]