{
    "ForgeSpecContainerId":9,
    "MinCraftQuality":"Magic",
    "MinReforgeQuality":"Magic",
    "MaxForgeItemLevel":30,
    "CraftTable":{
        "ShouldShowFinishNowOption":true,
        "BuildingNotificationIconUrl":"blacksmith\/hudfinishicons\/craft.png",
        "BuildingProgressBarIconUrl":"blacksmith\/hudprogressicons\/craft.png",
        "TierTable":
        {
            "Magic":{
                "Duration":"3s",
                "RequiredItemCount":6,
                "BuildingRankRequirement":1,
                "LevelToChanceModifiers":
                {
                    "0":0.75,
                    "1":0.2,
                    "2":0.045,
                    "3":0.005
                },
                "ItemClassTable":{
                    "HeroPlayedByUser":1,
                    "BonusPerLowLevel":0.05,
                    "LootableHeroSpecIds":
                    [
                        2,
                        3,
                        4,
                        5
                    ]
                },
                "OptionOasisId":14047,
                "ShopConfirmationOasisId":15270,
                "ShopConfirmationShopIconUrl":"blacksmith\/mysteryitembox\/magic.png"
            },
            "Exceptional":{
                "Duration":"3s",
                "RequiredItemCount":5,
                "BuildingRankRequirement":2,
                "LevelToChanceModifiers":
                {
                    "0":0.75,
                    "1":0.2,
                    "2":0.045,
                    "3":0.005
                },
                "ItemClassTable":{
                    "HeroPlayedByUser":1,
                    "BonusPerLowLevel":0.05,
                    "LootableHeroSpecIds":
                    [
                        2,
                        3,
                        4,
                        5
                    ]
                },
                "OptionOasisId":14048,
                "ShopConfirmationOasisId":15272,
                "ShopConfirmationShopIconUrl":"blacksmith\/mysteryitembox\/exceptional.png"
            },
            "Legendary":{
                "Duration":"2h",
                "RequiredItemCount":4,
                "BuildingRankRequirement":3,
                "LevelToChanceModifiers":
                {
                    "0":0.75,
                    "1":0.2,
                    "2":0.045,
                    "3":0.005
                },
                "ItemClassTable":{
                    "HeroPlayedByUser":1,
                    "BonusPerLowLevel":0.05,
                    "LootableHeroSpecIds":
                    [
                        2,
                        3,
                        4,
                        5
                    ]
                },
                "OptionOasisId":14049,
                "ShopConfirmationOasisId":15271,
                "ShopConfirmationShopIconUrl":"blacksmith\/mysteryitembox\/legendary.png"
            },
            "Epic":{
                "Duration":"4h",
                "RequiredItemCount":3,
                "BuildingRankRequirement":4,
                "LevelToChanceModifiers":
                {
                    "0":0.75,
                    "1":0.2,
                    "2":0.045,
                    "3":0.005
                },
                "ItemClassTable":{
                    "HeroPlayedByUser":1,
                    "BonusPerLowLevel":0.05,
                    "LootableHeroSpecIds":
                    [
                        2,
                        3,
                        4,
                        5
                    ]
                },
                "OptionOasisId":14050,
                "ShopConfirmationOasisId":15273,
                "ShopConfirmationShopIconUrl":"blacksmith\/mysteryitembox\/epic.png"
            }
        }
    },
    "ReforgeTable":{
        "ShouldShowFinishNowOption":true,
        "BuildingNotificationIconUrl":"blacksmith\/hudfinishicons\/reforge.png",
        "BuildingProgressBarIconUrl":"blacksmith\/hudprogressicons\/reforge.png",
        "TierTable":
        {
            "Magic":{
                "Duration":"3s",
                "RequiredItemCount":1,
                "BuildingRankRequirement":1,
                "LevelToChanceModifiers":
                {
                    "0":1
                },
                "ItemClassTable":{
                    "HeroPlayedByUser":1,
                    "BonusPerLowLevel":0.05,
                    "LootableHeroSpecIds":
                    [
                        2,
                        3,
                        4,
                        5
                    ]
                },
                "OptionOasisId":14047,
                "ShopConfirmationOasisId":15270,
                "ShopConfirmationShopIconUrl":"blacksmith\/mysteryitembox\/magic.png"
            },
            "Exceptional":{
                "Duration":"3s",
                "RequiredItemCount":1,
                "BuildingRankRequirement":2,
                "LevelToChanceModifiers":
                {
                    "0":1
                },
                "ItemClassTable":{
                    "HeroPlayedByUser":1,
                    "BonusPerLowLevel":0.05,
                    "LootableHeroSpecIds":
                    [
                        2,
                        3,
                        4,
                        5
                    ]
                },
                "OptionOasisId":14048,
                "ShopConfirmationOasisId":15272,
                "ShopConfirmationShopIconUrl":"blacksmith\/mysteryitembox\/exceptional.png"
            },
            "Legendary":{
                "Duration":"30m",
                "RequiredItemCount":1,
                "BuildingRankRequirement":3,
                "LevelToChanceModifiers":
                {
                    "0":1
                },
                "ItemClassTable":{
                    "HeroPlayedByUser":1,
                    "BonusPerLowLevel":0.05,
                    "LootableHeroSpecIds":
                    [
                        2,
                        3,
                        4,
                        5
                    ]
                },
                "OptionOasisId":14049,
                "ShopConfirmationOasisId":15271,
                "ShopConfirmationShopIconUrl":"blacksmith\/mysteryitembox\/legendary.png"
            },
            "Epic":{
                "Duration":"2h",
                "RequiredItemCount":1,
                "BuildingRankRequirement":4,
                "LevelToChanceModifiers":
                {
                    "0":1
                },
                "ItemClassTable":{
                    "HeroPlayedByUser":1,
                    "BonusPerLowLevel":0.05,
                    "LootableHeroSpecIds":
                    [
                        2,
                        3,
                        4,
                        5
                    ]
                },
                "OptionOasisId":14050,
                "ShopConfirmationOasisId":15273,
                "ShopConfirmationShopIconUrl":"blacksmith\/mysteryitembox\/epic.png"
            }
        }
    },
    "UpgradeTable":{
        "BuildingNotificationIconUrl":"blacksmith\/hudfinishicons\/up.png",
        "BuildingProgressBarIconUrl":"blacksmith\/hudprogressicons\/enchant.png",
        "TierTable":
        {
            "Magic":{
                "Duration":"3s",
                "RequiredItemCount":1,
                "BuildingRankRequirement":1,
                "LevelToChanceModifiers":
                {
                    "1":1
                },
                "OptionOasisId":14047,
                "ShopConfirmationOasisId":15270,
                "ShopConfirmationShopIconUrl":"blacksmith\/mysteryitembox\/magic.png"
            },
            "Exceptional":{
                "Duration":"3s",
                "RequiredItemCount":1,
                "BuildingRankRequirement":1,
                "LevelToChanceModifiers":
                {
                    "1":1
                },
                "OptionOasisId":14048,
                "ShopConfirmationOasisId":15272,
                "ShopConfirmationShopIconUrl":"blacksmith\/mysteryitembox\/exceptional.png"
            },
            "Legendary":{
                "Duration":"3s",
                "RequiredItemCount":1,
                "BuildingRankRequirement":1,
                "LevelToChanceModifiers":
                {
                    "1":1
                },
                "OptionOasisId":14049,
                "ShopConfirmationOasisId":15271,
                "ShopConfirmationShopIconUrl":"blacksmith\/mysteryitembox\/legendary.png"
            },
            "Epic":{
                "Duration":"3s",
                "RequiredItemCount":1,
                "BuildingRankRequirement":1,
                "LevelToChanceModifiers":
                {
                    "1":1
                },
                "OptionOasisId":14050,
                "ShopConfirmationOasisId":15273,
                "ShopConfirmationShopIconUrl":"blacksmith\/mysteryitembox\/epic.png"
            }
        }
    },
    "PropertyLevelUpChances":
    [
        {
            "LevelFrom":11,
            "LevelTo":15,
            "PropertyLevel":1,
            "Chance":0.3
        },
        {
            "LevelFrom":16,
            "LevelTo":20,
            "PropertyLevel":1,
            "Chance":0.6
        },
        {
            "LevelFrom":16,
            "LevelTo":20,
            "PropertyLevel":2,
            "Chance":0.3
        },
        {
            "LevelFrom":21,
            "LevelTo":30,
            "PropertyLevel":1,
            "Chance":0.8
        },
        {
            "LevelFrom":21,
            "LevelTo":30,
            "PropertyLevel":2,
            "Chance":0.6
        },
        {
            "LevelFrom":21,
            "LevelTo":30,
            "PropertyLevel":3,
            "Chance":0.3
        }
    ],
    "AssignmentCompletedForRegularForge":2000,
    "EffectModifierTable":
    {
        "0":0,
        "3":0.4
    }
}