[
    {
        "$type":"HyperQuest.GameServer.Contracts.VisualSpec, HyperQuest.GameServer.Contracts",
        "SynergyName":"Totem_ActivationShockwave",
        "SynergyEntityFileName":"DB:>RAW>GEOMETRIES>MESH_203B0F5A>MESH_203B0F5A.MESH",
        "Scale":0.3
    },
    {
        "$type":"HyperQuest.GameServer.Contracts.VisualFieldFxSpec, HyperQuest.GameServer.Contracts",
        "FieldShowFx":
        [
            {
                "$type":"HyperQuest.GameServer.Contracts.VisualSpecialEffectNodeFxSpec, HyperQuest.GameServer.Contracts",
                "SynergyEntityFileName":"DB:>RAW>SPECIALEFFECTS>SPECIALFX_35223247_BD346>SPECIALFX_35223247_BD346.SPECIALFX",
                "AttachmentStrategy":{
                    "$type":"HyperQuest.GameServer.Contracts.VisualNodeAttachmentStrategySpec, HyperQuest.GameServer.Contracts",
                    "StickToTheWorld":true
                },
                "ForcePlayUntilFxFinished":true
            }
        ]
    }
]